ron/aihelpers/__init__.py
ron/aihelpers/keras.py
ron/aihelpers/setup.py
ron/datasources/__init__.py
ron/datasources/datasources.py
ron/datasources/iex.py
ron-0.0.1.dist-info/METADATA
ron-0.0.1.dist-info/WHEEL
ron-0.0.1.dist-info/top_level.txt
ron-0.0.1.dist-info/RECORD
