Metadata-Version: 2.1
Name: ron
Version: 0.0.1
Summary: Python Helper Modules
Home-page: https://github.com/ronaldocpontes/python-notebooks
License: MIT
Platform: UNKNOWN
Classifier: License :: OSI Approved :: MIT License
Classifier: Programming Language :: Python :: 3
Classifier: Programming Language :: Python :: 3.7
Classifier: Operating System :: OS Independent
Provides-Extra: dev
Requires-Dist: pytest ; extra == 'dev'
Requires-Dist: tox ; extra == 'dev'
